source_genesys/__init__.py
source_genesys/authenicator.py
source_genesys/run.py
source_genesys/schemas/routing_outbound_events.json
source_genesys/schemas/routing_routing_assessments.json
source_genesys/schemas/routing_routing_queues.json
source_genesys/schemas/telephony_locations.json
source_genesys/schemas/telephony_providers_edges.json
source_genesys/schemas/telephony_providers_edges_didpools.json
source_genesys/schemas/telephony_providers_edges_dids.json
source_genesys/schemas/telephony_providers_edges_extensions.json
source_genesys/schemas/telephony_providers_edges_lines.json
source_genesys/schemas/telephony_providers_edges_outboundroutes.json
source_genesys/schemas/telephony_providers_edges_phones.json
source_genesys/schemas/telephony_providers_edges_sites.json
source_genesys/schemas/telephony_providers_edges_trunks.json
source_genesys/schemas/telephony_stations.json
source_genesys/schemas/user_groups.json
source_genesys/schemas/user_users.json
source_genesys/source.py
source_genesys/spec.json
airbyte_source_genesys-0.1.41.dist-info/METADATA
airbyte_source_genesys-0.1.41.dist-info/WHEEL
airbyte_source_genesys-0.1.41.dist-info/entry_points.txt
airbyte_source_genesys-0.1.41.dist-info/RECORD
